{
  "seller": [
    {
      "name": "nikhil",
      "password": "nikhil@123",
      "email": "nikhilbankar7@gmail.com"
    },
    {
      "name": "tejas",
      "password": "te123",
      "email": "te@gmail.com",
      "id": 2
    },
    {
      "name": "swapnil",
      "password": "swapnil123",
      "email": "swapnil@gmail.com",
      "id": 3
    },
    {
      "name": "swapnil",
      "password": "swapnil123",
      "email": "swapnil@gmail.com",
      "id": 4
    },
    {
      "name": "",
      "password": "",
      "email": "",
      "id": 5
    },
    {
      "name": "dd",
      "password": "asdfgh",
      "email": "aer@gmail.com",
      "id": 6
    },
    {
      "name": "dd",
      "password": "wertyu",
      "email": "dd@gmail.com",
      "id": 7
    },
    {
      "name": "",
      "password": "",
      "email": "",
      "id": 8
    },
    {
      "name": "",
      "password": "",
      "email": "",
      "id": 9
    },
    {
      "name": "viplav",
      "password": "viplav123",
      "email": "viplav@gmail.com",
      "id": 10
    }
  ],
  "products": [
    {
      "productName": "samsung",
      "productPrice": "23000",
      "productColor": "black",
      "productCategory": "mobile",
      "productDescription": "mobile added",
      "image": "https://media.istockphoto.com/id/1217881331/photo/man-holding-in-hands-samsung-galaxy-s20-ultra-closeup.jpg?s=612x612&w=0&k=20&c=BhMtzBJQC-D5jNfYfb6vIr4K7vV4INyZ7UzWXkI51EE=",
      "id": 1
    },
    {
      "productName": "Oppo",
      "productPrice": "24999",
      "productColor": "silver",
      "productCategory": "mobile",
      "productDescription": "8gb Ram, 128gb internal sotrage",
      "image": "https://cdn.pixabay.com/photo/2019/08/22/12/09/coffee-4423348__340.jpg",
      "id": 2
    }
  ]
}